archive_to_s3/__init__.py
archive_to_s3/process.py
archive_to_s3-1.0.5.dist-info/METADATA
archive_to_s3-1.0.5.dist-info/WHEEL
archive_to_s3-1.0.5.dist-info/entry_points.txt
archive_to_s3-1.0.5.dist-info/top_level.txt
archive_to_s3-1.0.5.dist-info/RECORD
