Metadata-Version: 2.1
Name: archive-to-s3
Version: 1.0.5
Summary: UNKNOWN
Home-page: https://github.com/davidfischer-ch/archive-to-s3
Author: David Fischer
Author-email: david@fisch3r.net
License: EUPL 1.1
Keywords: archive,aws,s3
Platform: UNKNOWN
Classifier: Development Status :: 5 - Production/Stable
Classifier: Intended Audience :: Developers
Classifier: License :: OSI Approved :: European Union Public Licence 1.1 (EUPL 1.1)
Classifier: Natural Language :: English
Classifier: Operating System :: POSIX :: Linux
Classifier: Programming Language :: Python :: 3
Classifier: Programming Language :: Python :: 3.3
Classifier: Programming Language :: Python :: 3.4
Classifier: Programming Language :: Python :: 3.5
Classifier: Programming Language :: Python :: 3.6
Classifier: Programming Language :: Python :: Implementation :: CPython
Classifier: Programming Language :: Python :: Implementation :: PyPy
Classifier: Topic :: System :: Archiving
Classifier: Topic :: System :: Archiving :: Backup
Classifier: Topic :: System :: Archiving :: Mirroring
Requires-Dist: pytoolbox[aws] (>=13.0.4<14)
Requires-Dist: JSON-log-formatter (>=0.2.0<1.0)
